flatapi/__init__.py
flatapi/__main__.py
flatapi/methods.py
flatapi/resource.py
flatapi/settings.py
flatapi-6.2.0.dist-info/DESCRIPTION.rst
flatapi-6.2.0.dist-info/METADATA
flatapi-6.2.0.dist-info/RECORD
flatapi-6.2.0.dist-info/WHEEL
flatapi-6.2.0.dist-info/metadata.json
flatapi-6.2.0.dist-info/top_level.txt
flatapi-6.2.0.dist-info/zip-safe
tests/__init__.py
tests/test_api.py
tests/test_api_cfg_momery_storage.py
tests/test_api_no_cfg.py
tests/test_api_prefix.py
tests/test_api_prefix_no_cfg.py
tests/test_flatapi.py
tests/test_methods.py
tests/test_resource.py
